{
  "backtest_type": "daily_only_ema_crossover",
  "strategy_name": "Daily EMA Crossover (20/50)",
  "timeframe": "Daily",
  "backtest_date": "2025-08-20T08:16:54.927158+00:00",
  "total_pairs": 10,
  "successful_pairs": 10,
  "portfolio_return": 11.816705593075449,
  "portfolio_win_rate": 32.299741602067186,
  "portfolio_sharpe": 0.05960630754265145,
  "portfolio_max_drawdown": 26.948645301949515,
  "total_trades": 387,
  "risk_assessment": "Medium",
  "performance_grade": "B",
  "top_performers": [
    {
      "pair": "USD_JPY",
      "return": 52.46528985583551,
      "win_rate": 50.0,
      "sharpe": 0.3283383281836537,
      "trades": 28,
      "grade": "B"
    },
    {
      "pair": "GBP_USD",
      "return": 44.57469389459899,
      "win_rate": 44.44444444444444,
      "sharpe": 0.3198392137676768,
      "trades": 36,
      "grade": "C"
    },
    {
      "pair": "EUR_USD",
      "return": 20.506466252710815,
      "win_rate": 33.33333333333333,
      "sharpe": 0.15030987150767847,
      "trades": 42,
      "grade": "D"
    }
  ]
}